[
  {
    "date" : "Today",
    "events":[
      {
        "isNotification"    :true,
        "actor"       : "Jeremy B.",
        "actorImg"    : "_assets/img/jeremy.jpg",
        "item"        : "Portland Bicycle Parking",
        "linkable"    : true,
        "itemThumb"   : "https://www.arcgis.com/sharing/rest/content/items/b67bc6da241640808b7762b65a66f9e2/info/thumbnail/ago_downloaded.png",
        "itemType"    : "feature layer",
        "actions"     : [],
        "message"     : "will be <span class=\"event-count\">unavailable in 7 Days</span>.",
        "actionType"  : "minus-circled",
        "actionable"   :true,
        "following"   : false,
        "followID"    : "pbp-001",
        "actionTime"  : "<span class=\"notification-date hide\">Oct 27<br/></span>Just now",
        "dateStamp"   : "Oct 5, 2015, 03:00PM PST",
        "archived"    : "false",
        "unread"      : "true"
        },
      {
        "isNotification"    :true,
        "actor"       : "Heath M.",
        "actorImg"    : "https://media.licdn.com/mpr/mpr/shrinknp_400_400/p/5/005/031/071/23507a0.jpg",
        "item"        : "Site Planning (Old)",
        "linkable"    : false,
        "itemThumb"   : "",
        "itemType"    : "group",
        "actions"     : [],
        "message"     : "was removed from <a class=\"item-type\">SDGE Solar</a>.",
        "actionType"  : "group",
        "actionable"   :false,
        "following"   : false,
        "followID"    : null,
        "actionTime"  : "<span class=\"notification-date hide\">Oct 27</span>9m",
        "dateStamp"   :"Oct 5, 2015, 03:00PM PST",
        "archived"    : "false",
        "unread"      : "true"
        },
      {
        "isNotification"    :true,
        "actor"       : "Erich R.",
        "actorImg"    : "http://dc.esri.com/assets/img/profile-bluedog.jpg",
        "item"        : "Solar Analysis FS-2112",
        "linkable"    : true,
        "itemThumb"   : "",
        "itemType"    : "feature layer",
        "actions"     : [],
        "message"     : "was shared with <span class=\"item-type\">Public</span>.",
        "actionType"  : "share",
        "actionable"   :false,
        "following"   : false,
        "followID"    : null,
        "actionTime"  : "<span class=\"notification-date hide\">Oct 26</span>1h",
        "dateStamp"   :"Oct 26, 2015, 04:13PM PST",
        "archived"    : "false",
        "unread"      : "true"
        },
      {
        "isNotification"    :true,
        "actor"       : "Mark H.",
        "actorImg"    : "https://avatars1.githubusercontent.com/u/5749836",
        "item"        : "Mark H.",
        "linkable"    : true,
        "itemThumb"   : "",
        "itemType"    : "user",
        "actions"     : [],
        "message"     : "would like to join <a class=\"item-type\">SDGE Solar</a>.",
        "actionType"  : "user",
        "actionable"   :true,
        "following"   : false,
        "followID"    : null,
        "actionTime"  : "<span class=\"notification-date hide\">Oct 27</span>2h",
        "dateStamp"   :"Oct 5, 2015, 12:32PM PST",
        "archived"    : "false"
        },
      {
        "isNotification"    :true,
        "actor"       : "Erich R.",
        "actorImg"    : "http://dc.esri.com/assets/img/profile-bluedog.jpg",
        "item"        : "Glasgow, Scotland - Port Dundas Business Park, Financial Commercial Survey Application",
        "linkable"    : false,
        "itemThumb"   : "https://www.arcgis.com/sharing/rest/content/items/7fce663d57484a32a4afe3f0c2233e82/info/thumbnail/ago_downloaded.png",
        "itemType"    : "feature layer",
        "actions"     : [],
        "message"     : "is no longer available to you.",
        "actionType"  : "minus-circled",
        "actionable"   :true,
        "following"   : false,
        "followID"    : "glasgow",
        "actionTime"  : "<span class=\"notification-date\">Oct 27<br/></span>9:32am",
        "dateStamp"   :"Oct 5, 2015, 03:00PM PST",
        "archived"    : "false"
        },
      {
        "isNotification"    :true,
        "actor"       : "SDGE Solar",
        "actorImg"    : "http://dummyimage.com/50/6e6e6e/fff.png&text=SDGE",
        "item"        : "SDGE Solar",
        "linkable"    : true,
        "itemThumb"   : "",
        "itemType"    : "org",
        "actions"     : [],
        "message"     : "is scheduled for <span class=\"item-type\">maintenance</span> 01:00hrs on <span class=\"item-type\">10/30/2015</span>.",
        "actionType"  : "notice-triangle",
        "actionable"   :false,
        "following"   : false,
        "followID"    : null,
        "actionTime"  : "<span class=\"notification-date \">Oct 27<br/></span>8:13am",
        "dateStamp"   :"Oct 26, 2015, 09:13AM PST",
        "archived"    : "true"
        },
      {
        "isNotification"    :true,
        "actor"       : "Frank G.",
        "actorImg"    : "https://pbs.twimg.com/profile_images/426595958168641536/0XI1xmhE.jpeg",
        "item"        : "Charging Stations, CA",
        "linkable"    : true,
        "itemThumb"   : "",
        "itemType"    : "feature layer",
        "actions"     : [],
        "message"     : "will be <span class=\"event-count\">unavailable in 14 Days</span>.",
        "actionType"  : "minus-circled",
        "actionable"   :true,
        "following"   : false,
        "followID"    : null,
        "actionTime"  : "<span class=\"notification-date\">Oct 26<br/></span>3:13pm",
        "dateStamp"   :"Oct 25, 2015, 03:13PM PST",
        "archived"    : "false"
        },
      {
        "isNotification"    :true,
        "actor"       : "SDGE Solar",
        "actorImg"    : "http://dummyimage.com/50/6e6e6e/fff.png&text=%20SDGE%20",
        "item"        : "SDGE Solar",
        "linkable"    : true,
        "itemThumb"   : "",
        "itemType"    : "account",
        "actions"     : [],
        "message"     : "is nearing its <span class=\"event-count\">credit limit</span>.",
        "actionType"  : "organization",
        "actionable"   :true,
        "following"   : false,
        "followID"    : null,
        "actionTime"  : "<span class=\"notification-date\">Oct 26<br/></span>2:10pm",
        "dateStamp"   :"Oct 25, 2015, 02:10PM PST",
        "archived"    : "false"
        },
      {
        "isNotification"    :true,
        "actor"       : "Sentha S.",
        "actorImg"    : "https://media.licdn.com/media/p/3/000/0ed/072/0793423.jpg",
        "item"        : "A source layer",
        "linkable"    : false,
        "itemThumb"   : "",
        "itemType"    : "feature layer",
        "actions"     : [],
        "message"     : "removed and used by <a class=\"item-type\">Power Stations</a>.",
        "actionType"  : "minus-circled",
        "actionable"   :true,
        "following"   : false,
        "followID"    : null,
        "actionTime"  : "<span class=\"notification-date\">Oct 25<br/></span>9:10am",
        "dateStamp"   :"Oct 26, 2015, 09:10AM PST",
        "archived"    : "true"
        },
      {
        "isNotification"    :true,
        "actor"       : "Alan S.",
        "actorImg"    : "https://media.licdn.com/mpr/mpr/shrinknp_400_400/AAEAAQAAAAAAAAMzAAAAJDZmYTA0OTlhLTgwMzMtNDJhZC1hNjQxLWJjMDE0NzcyZDY5Ng.jpg",
        "item"        : "Planning Advisory",
        "linkable"    : true,
        "itemThumb"   : "",
        "itemType"    : "group",
        "actions"     : [],
        "message"     : "added to <a class=\"item-type\">SDGE Solar</a>.",
        "actionType"  : "plus-circled",
        "actionable"   :true,
        "following"   : false,
        "followID"    : null,
        "actionTime"  : "<span class=\"notification-date\">Oct 23<br/></span>10:47am",
        "dateStamp"   :"Oct 26, 2015, 09:10AM PST",
        "archived"    : "true"
        },
      {
        "isNotification"    :true,
        "actor"       : "System",
        "actorImg"    : "http://dummyimage.com/50/6e6e6e/fff.png&text=%20SDGE%20",
        "item"        : "Job \"Buffer 100 miles\"",
        "linkable"    : true,
        "itemThumb"   : "",
        "itemType"    : "process",
        "actions"     : [],
        "message"     : " on Layer <a class=\"item-type\">Power Stations</a> finished.",
        "actionType"  : "check-mark",
        "actionable"   :true,
        "following"   : false,
        "followID"    : null,
        "actionTime"  : "<span class=\"notification-date\">Oct 23<br/></span>8:27am",
        "dateStamp"   :"Oct 26, 2015, 09:10AM PST",
        "archived"    : "true"
        },
      {
        "actor"       : "Sentha S. ",
        "actorImg"    : "https://media.licdn.com/media/p/3/000/0ed/072/0793423.jpg",
        "item"        : "Street Permits Jobs",
        "linkable"    : true,
        "itemThumb"   : "https://www.arcgis.com/sharing/rest/content/items/ed82f763d4604f669680525912d51b1f/info/thumbnail/ago_downloaded.png",
        "itemType"    : "feature layer",
        "actions"     : [
                          "<span class=\"event-count\">7</span> <span class=\"event-feature item-type\">Features</span> added",
                          "<span class=\"event-count\">1</span> <span class=\"event-feature item-type\">Feature</span> deleted"
                        ],
        "message"     : null,
        "actionType"  : "edit",
        "following"   : false,
        "followID"    : "spjp",
        "actionTime"  : "5m",
        "dateStamp"   :"Oct 5, 2015, 03:00PM PST"
        },
      {
        "actor"       : "Mark H.",
        "actorImg"    : "https://avatars1.githubusercontent.com/u/5749836",
        "item"        : "Largest-Urban-Areas",
        "linkable"    : true,
        "itemThumb"   : "https://www.arcgis.com/sharing/rest/content/items/b67bc6da241640808b7762b65a66f9e2/info/thumbnail/ago_downloaded.png",
        "itemType"    : "map",
        "actions"     : ["shared with <span class=\"item-type\">Public</span>"],
        "message"     : "",
        "actionType"  : "share",
        "actionable"   :false,
        "following"   : true,
        "followID"    : "lua-001",
        "actionTime"  : "12m",
        "dateStamp"   :"Oct 5, 2015, 03:00PM PST"
        },
      {
        "actor"       : "Heath M.",
        "actorImg"    : "https://media.licdn.com/mpr/mpr/shrinknp_400_400/p/5/005/031/071/23507a0.jpg",
        "item"        : "Site Planning",
        "linkable"    : true,
        "itemThumb"   : "",
        "itemType"    : "group",
        "actions"     : [
                            "added to <a class=\"item-type\">SDGE Solar</a>"
                        ],
        "message"     : "",
        "actionType"  : "group",
        "actionable"   :false,
        "following"   : false,
        "followID"    : "site-planning",
        "actionTime"  : "1h",
        "dateStamp"   :"Oct 5, 2015, 03:00PM PST"
        },
      {
        "actor"       : "Sentha S.",
        "actorImg"    : "https://media.licdn.com/media/p/3/000/0ed/072/0793423.jpg",
        "item"        : "Portland Parks Water Usage",
        "linkable"    : true,
        "itemThumb"   : "https://www.arcgis.com/sharing/rest/content/items/011a7aa51f134f03b079fc7cdc633bb0/info/thumbnail/ago_downloaded.png",
        "itemType"    : "feature layer",
        "actions"     : [
                          "<span class=\"event-count\">2</span> <span class=\"event-layer item-type\">Layers</span> added",
                          "<span class=\"event-count\">23</span> <span class=\"event-feature item-type\">Features</span> modified"
                        ],
        "message"     : null,
        "actionType"  : "edit",
        "following"   : false,
        "followID"    : "prtprks",
        "actionTime"  : "2:15pm",
        "dateStamp"   :"Oct 5, 2015, 03:00PM PST"
        },
      {
        "actor"       : "Patrick A.",
        "actorImg"    : "_assets/img/gravatar.jpg",
        "item"        : "Portland Parks",
        "linkable"    : true,
        "itemThumb"   : "https://www.arcgis.com/sharing/rest/content/items/011a7aa51f134f03b079fc7cdc633bb0/info/thumbnail/ago_downloaded.png",
        "itemType"    : "map",
        "actions"     : [
                          "shared with <span class=\"item-type\">3 Groups</span>",
                          "shared with <span class=\"item-type\">Public</span>"
                        ],
        "message"     : null,
        "actionType"  : "share",
        "following"   : false,
        "followID"    : "prtprks",
        "actionTime"  : "12:48pm",
        "dateStamp"   :"Oct 5, 2015, 03:00PM PST"
        },
      {
        "actor"       : "Frank G.",
        "actorImg"    : "https://pbs.twimg.com/profile_images/426595958168641536/0XI1xmhE.jpeg",
        "item"        : "Portland Parks",
        "linkable"    : true,
        "itemThumb"   : "https://www.arcgis.com/sharing/rest/content/items/011a7aa51f134f03b079fc7cdc633bb0/info/thumbnail/ago_downloaded.png",
        "itemType"    : "map",
        "actions"     : [
                          "modified"
                        ],
        "message"     : null,
        "actionType"  : "edit",
        "following"   : false,
        "followID"    : "prtprks",
        "actionTime"  : "11:58am",
        "dateStamp"   :"Oct 5, 2015, 03:00PM PST"
        },
      {
        "actor"       : "Patrick A.",
        "actorImg"    : "_assets/img/gravatar.jpg",
        "item"        : "Street Permits Jobs",
        "linkable"    : true,
        "itemThumb"   : "https://www.arcgis.com/sharing/rest/content/items/ed82f763d4604f669680525912d51b1f/info/thumbnail/ago_downloaded.png",
        "itemType"    : "feature layer",
        "actions"     : [
                          "<span class=\"event-count\">7</span> <span class=\"event-feature item-type\">Features</span> added",
                          "<span class=\"event-count\">1</span> <span class=\"event-feature item-type\">Feature</span> deleted",
                          "<span class=\"event-count\">1</span> <span class=\"event-layer item-type\">Layer</span> removed",
                          "<span class=\"item-type event-scheme\">Schema</span> modified",
                          "<span class=\"item-type\">Renderer</span> modified"
                          ],
        "message"     : null,
        "actionType"  : "edit",
        "following"   : false,
        "followID"    : "spjp",
        "actionTime"  : "10:13am",
        "dateStamp"   :"Oct 5, 2015, 03:00PM PST"
        }
    ]
    },
  {
    "date" : "Yesterday",
    "events" : [
      {
        "actor"       : "Mark H.",
        "actorImg"    : "https://avatars1.githubusercontent.com/u/5749836",
        "item"        : "Largest-Urban-Areas",
        "linkable"    : true,
        "itemThumb"   : "https://www.arcgis.com/sharing/rest/content/items/b67bc6da241640808b7762b65a66f9e2/info/thumbnail/ago_downloaded.png",
        "itemType"    : "map",
        "actions"     : ["modified"],
        "message"     : "modified",
        "actionType"  : "edit",
        "actionable"   :false,
        "following"   : true,
        "followID"    : "lua-001",
        "actionTime"  : "5:27pm",
        "dateStamp"   :"Oct 5, 2015, 03:00PM PST"
        },
      {
        "actor"       : "Alan S.",
        "actorImg"    : "https://media.licdn.com/mpr/mpr/shrinknp_400_400/AAEAAQAAAAAAAAMzAAAAJDZmYTA0OTlhLTgwMzMtNDJhZC1hNjQxLWJjMDE0NzcyZDY5Ng.jpg",
        "item"        : "Street Permits Jobs",
        "linkable"    : true,
        "itemThumb"   : "https://www.arcgis.com/sharing/rest/content/items/ed82f763d4604f669680525912d51b1f/info/thumbnail/ago_downloaded.png",
        "itemType"    : "feature layer",
        "actions"     : ["This <span class=\"item-type\">feature layer</span> was created."],
        "message"     : null,
        "actionType"  : "plus-circled",
        "following"   : false,
        "followID"    : "spjp",
        "actionTime"  : "4:52pm",
        "dateStamp"   :"Oct 5, 2015, 03:00PM PST"
      },
      {
        "actor"       : "Heath M.",
        "actorImg"    : "https://media.licdn.com/mpr/mpr/shrinknp_400_400/p/5/005/031/071/23507a0.jpg",
        "item"        : "Portland Parks",
        "linkable"    : true,
        "itemThumb"   : "https://www.arcgis.com/sharing/rest/content/items/011a7aa51f134f03b079fc7cdc633bb0/info/thumbnail/ago_downloaded.png",
        "itemType"    : "map",
        "actions"     : [
                          "This <span class=\"item-type\">map</span> was created."
                        ],
        "message"     : null,
        "actionType"  : "plus-circled",
        "following"   : false,
        "followID"    : "prtprks",
        "actionTime"  : "4:12pm",
        "dateStamp"   :"Oct 5, 2015, 03:00PM PST"
        },
      {
        "actor"       : "Frank G.",
        "actorImg"    : "https://pbs.twimg.com/profile_images/426595958168641536/0XI1xmhE.jpeg",
        "item"        : "Capital Improvement Projects (CIP) Lines",
        "linkable"    : true,
        "itemThumb"   : "https://www.arcgis.com/sharing/rest/content/items/93ed0b190bc6441fad1e48871b4c58d2/info/thumbnail/ago_downloaded.png",
        "itemType"    : "feature layer",
        "actions"     : ["<span class=\"item-type\">title</span> modified from \"CIP Lines\""],
        "message"     : null,
        "actionType"  : "edit",
        "following"   : true,
        "followID"    : "cip-lines",
        "actionTime"  : "11:17am",
        "dateStamp"   :"Oct 5, 2015, 03:00PM PST"
        },
      {
        "actor"       : "Alan S.",
        "actorImg"    : "https://media.licdn.com/mpr/mpr/shrinknp_400_400/AAEAAQAAAAAAAAMzAAAAJDZmYTA0OTlhLTgwMzMtNDJhZC1hNjQxLWJjMDE0NzcyZDY5Ng.jpg",
        "item"        : "Portland Bicycle Network",
        "linkable"    : true,
        "itemThumb"   : "https://www.arcgis.com/sharing/rest/content/items/191e7d0605a24a7ea42e802b4d5742bb/info/thumbnail/ago_downloaded.png",
        "itemType"    : "feature layer",
        "actions"     : ["<span class=\"item-type\">access</span> changed to <span class=\"item-type\">private</span>"],
        "message"     : null,
        "actionType"  : "share",
        "following"   : false,
        "followID"    : "pbn",
        "actionTime"  : "9:20am",
        "dateStamp"   :"Oct 5, 2015, 03:00PM PST"
        },
      {
        "actor"       : "Sentha S.",
        "actorImg"    : "https://media.licdn.com/media/p/3/000/0ed/072/0793423.jpg",
        "item"        : "Heritage Trees Portland",
        "linkable"    : true,
        "itemThumb"   : "https://www.arcgis.com/sharing/rest/content/items/a539e9fe98964fbca427fe84629db1be/info/thumbnail/ago_downloaded.png",
        "itemType"    : "feature layer",
        "actions"     : ["This <span class=\"item-type\">feature layer</span> was created."],
        "message"     : null,
        "actionType"  : "plus-circled",
        "following"   : false,
        "followID"    : "htp",
        "actionTime"  : "9:12am",
        "dateStamp"   :"Oct 5, 2015, 03:00PM PST"
      }
    ]
  }
]